lock_picker.py
lock_picker/lock-picker.py
lock_picker/lock_picker.py
lock_picker-1.1.dist-info/METADATA
lock_picker-1.1.dist-info/WHEEL
lock_picker-1.1.dist-info/entry_points.txt
lock_picker-1.1.dist-info/top_level.txt
lock_picker-1.1.dist-info/RECORD
